phenofeaturefinder/__init__.py
phenofeaturefinder/feature_selection_using_ml.py
phenofeaturefinder/omics_analysis.py
phenofeaturefinder/phenotype_analysis.py
phenofeaturefinder/utils.py
phenofeaturefinder-0.1.4.dist-info/LICENSE
phenofeaturefinder-0.1.4.dist-info/METADATA
phenofeaturefinder-0.1.4.dist-info/WHEEL
phenofeaturefinder-0.1.4.dist-info/RECORD
