Metadata-Version: 2.1
Name: PhenoFeatureFinder
Version: 0.1.4
Summary: Find metabolic features linked to insect development phenotypes
Home-page: https://github.com/BleekerLab/PhenoFeatureFinder
License: Apache-2.0
Author: Lissy-Anne Denkers
Requires-Python: >=3.9,<3.10
Classifier: License :: OSI Approved :: Apache Software License
Classifier: Programming Language :: Python :: 3
Classifier: Programming Language :: Python :: 3.9
Requires-Dist: TPOT (>=0.11.7)
Requires-Dist: matplotlib (>=3.4.3)
Requires-Dist: numpy (==1.25.0)
Requires-Dist: pandas (>=1.5.1)
Requires-Dist: scikit-learn (>=0.24.1)
Requires-Dist: scipy (>=1.10.1)
Requires-Dist: seaborn (>=0.12.1)
Requires-Dist: upsetplot (>=0.8.0)
Project-URL: Repository, https://github.com/BleekerLab/PhenoFeatureFinder
